theport/__init__.py
theport/scanner.py
theport/services.py
theport-2.1.1.dist-info/METADATA
theport-2.1.1.dist-info/WHEEL
theport-2.1.1.dist-info/top_level.txt
theport-2.1.1.dist-info/RECORD
