Metadata-Version: 2.1
Name: theport
Version: 2.1.1
Summary: A library for scanning ports and identifying services
Home-page: https://github.com/ByteBreach/theport
Author: MrFidal
Author-email: mrfidal@proton.me
Classifier: Programming Language :: Python :: 3
Classifier: License :: OSI Approved :: MIT License
Classifier: Operating System :: OS Independent
Requires-Python: >=3.6
Requires-Dist: requests
